whispersubs/__init__.py
whispersubs/__main__.py
whispersubs/_version.py
whispersubs-0.1.3.dist-info/METADATA
whispersubs-0.1.3.dist-info/WHEEL
whispersubs-0.1.3.dist-info/entry_points.txt
whispersubs-0.1.3.dist-info/licenses/LICENSE
whispersubs-0.1.3.dist-info/RECORD
