Metadata-Version: 2.3
Name: whispersubs
Version: 0.1.3
Summary: Transcribe audio/video files into subtitles
Project-URL: Homepage, https://github.com/andreabak/whispersubs
Project-URL: Documentation, https://github.com/andreabak/whispersubs#readme
Project-URL: Issues, https://github.com/andreabak/whispersubs/issues
Project-URL: Source, https://github.com/andreabak/whispersubs
Author-email: abk16 <and.theunnamed@gmail.com>
License: LGPL-3.0
License-File: LICENSE
Keywords: audio,subtitles,transcription,video,whisper
Classifier: Development Status :: 4 - Beta
Classifier: License :: OSI Approved :: GNU Lesser General Public License v3 (LGPLv3)
Classifier: Programming Language :: Python
Classifier: Programming Language :: Python :: 3.8
Classifier: Programming Language :: Python :: 3.9
Classifier: Programming Language :: Python :: 3.10
Classifier: Programming Language :: Python :: 3.11
Classifier: Programming Language :: Python :: 3.12
Classifier: Programming Language :: Python :: Implementation :: CPython
Requires-Python: >=3.8
Requires-Dist: blessed
Requires-Dist: enlighten
Requires-Dist: faster-whisper
Requires-Dist: numpy
Requires-Dist: pyav
Requires-Dist: srt
Provides-Extra: cuda
Requires-Dist: nvidia-cublas-cu12~=12.0; extra == 'cuda'
Requires-Dist: nvidia-cudnn-cu12~=8.0; extra == 'cuda'
Provides-Extra: dev
Requires-Dist: hatch; extra == 'dev'
Requires-Dist: pre-commit; extra == 'dev'
